envlock/__init__.py
envlock/cli.py
envlock/crypto.py
envlock/decrypt.py
envlock/encrypt.py
envlock/init.py
envlock/utils.py
envlock_kb-0.1.0.dist-info/licenses/LICENSE
envlock_kb-0.1.0.dist-info/METADATA
envlock_kb-0.1.0.dist-info/WHEEL
envlock_kb-0.1.0.dist-info/entry_points.txt
envlock_kb-0.1.0.dist-info/top_level.txt
envlock_kb-0.1.0.dist-info/RECORD
