Metadata-Version: 2.4
Name: envlock-kb
Version: 0.1.0
Summary: Secure environment variable management - Encrypt and decrypt .env files with AES-256-GCM
Home-page: https://github.com/kukilbharadwaj/envlock
Author: Kukil Bharadwaj
Author-email: kukilbharadwaj@example.com
License: MIT
Project-URL: Bug Tracker, https://github.com/kukilbharadwaj/envlock/issues
Project-URL: Documentation, https://github.com/kukilbharadwaj/envlock#readme
Project-URL: Source Code, https://github.com/kukilbharadwaj/envlock
Keywords: env,dotenv,secrets,encryption,cli,security,aes,environment-variables,configuration
Classifier: Development Status :: 4 - Beta
Classifier: Intended Audience :: Developers
Classifier: Topic :: Security :: Cryptography
Classifier: Topic :: Software Development :: Libraries :: Python Modules
Classifier: Topic :: System :: Systems Administration
Classifier: License :: OSI Approved :: MIT License
Classifier: Programming Language :: Python :: 3
Classifier: Programming Language :: Python :: 3.8
Classifier: Programming Language :: Python :: 3.9
Classifier: Programming Language :: Python :: 3.10
Classifier: Programming Language :: Python :: 3.11
Classifier: Programming Language :: Python :: 3.12
Classifier: Operating System :: OS Independent
Classifier: Environment :: Console
Requires-Python: >=3.8
License-File: LICENSE
Requires-Dist: cryptography>=41.0.0
Dynamic: author
Dynamic: author-email
Dynamic: classifier
Dynamic: description
Dynamic: description-content-type
Dynamic: home-page
Dynamic: keywords
Dynamic: license
Dynamic: license-file
Dynamic: project-url
Dynamic: requires-dist
Dynamic: requires-python
Dynamic: summary
